etc_jupyterlab_telemetry_library/__init__.py
etc_jupyterlab_telemetry_library/_version.py
etc_jupyterlab_telemetry_library/application.py
etc_jupyterlab_telemetry_library/handlers.py
etc_jupyterlab_telemetry_library-3.0.0.data/data/etc/jupyter/jupyter_notebook_config.d/etc_jupyterlab_telemetry_library.json
etc_jupyterlab_telemetry_library-3.0.0.data/data/etc/jupyter/jupyter_server_config.d/etc_jupyterlab_telemetry_library.json
etc_jupyterlab_telemetry_library-3.0.0.data/data/share/jupyter/labextensions/@educational-technology-collective/etc_jupyterlab_telemetry_library/package.json
etc_jupyterlab_telemetry_library-3.0.0.data/data/share/jupyter/labextensions/@educational-technology-collective/etc_jupyterlab_telemetry_library/schemas/@educational-technology-collective/etc_jupyterlab_telemetry_library/package.json.orig
etc_jupyterlab_telemetry_library-3.0.0.data/data/share/jupyter/labextensions/@educational-technology-collective/etc_jupyterlab_telemetry_library/schemas/@educational-technology-collective/etc_jupyterlab_telemetry_library/plugin.json
etc_jupyterlab_telemetry_library-3.0.0.data/data/share/jupyter/labextensions/@educational-technology-collective/etc_jupyterlab_telemetry_library/static/747.d3c939ccdb588e1b8370.js
etc_jupyterlab_telemetry_library-3.0.0.data/data/share/jupyter/labextensions/@educational-technology-collective/etc_jupyterlab_telemetry_library/static/799.d0740fa6889ffa3ac8ca.js
etc_jupyterlab_telemetry_library-3.0.0.data/data/share/jupyter/labextensions/@educational-technology-collective/etc_jupyterlab_telemetry_library/static/remoteEntry.02cfce1bea4c053ac855.js
etc_jupyterlab_telemetry_library-3.0.0.data/data/share/jupyter/labextensions/@educational-technology-collective/etc_jupyterlab_telemetry_library/static/style.js
etc_jupyterlab_telemetry_library-3.0.0.data/data/share/jupyter/labextensions/@educational-technology-collective/etc_jupyterlab_telemetry_library/static/third-party-licenses.json
etc_jupyterlab_telemetry_library-3.0.0.dist-info/METADATA
etc_jupyterlab_telemetry_library-3.0.0.dist-info/WHEEL
etc_jupyterlab_telemetry_library-3.0.0.dist-info/licenses/LICENSE
etc_jupyterlab_telemetry_library-3.0.0.dist-info/RECORD
